rut_miit_api/__init__.py
rut_miit_api-0.0.1.dev2.dist-info/LICENSE
rut_miit_api-0.0.1.dev2.dist-info/METADATA
rut_miit_api-0.0.1.dev2.dist-info/WHEEL
rut_miit_api-0.0.1.dev2.dist-info/RECORD
